covid19/__init__.py
covid19/admin.py
covid19/apps.py
covid19/filters.py
covid19/models.py
covid19/serializers.py
covid19/settings.py
covid19/signals.py
covid19/tests.py
covid19/urls.py
covid19/views.py
covid19/management/__init__.py
covid19/management/commands/__init__.py
covid19/management/commands/crawl.py
covid19/migrations/__init__.py
covid19/spider/nCoV/__init__.py
covid19/spider/nCoV/items.py
covid19/spider/nCoV/middlewares.py
covid19/spider/nCoV/pipelines.py
covid19/spider/nCoV/settings.py
covid19/spider/nCoV/spiders/__init__.py
covid19/spider/nCoV/spiders/__init__.pyc
covid19/spider/nCoV/spiders/dxy.py
covid19/spider/nCoV/spiders/dxy.pyc
covid19/spider/nCoV/spiders/__pycache__/__init__.cpython-36.pyc
covid19/spider/nCoV/spiders/__pycache__/dxy.cpython-36.pyc
covid19/tests/__init__.py
covid19/tests/test_statistics.py
django_covid19/__init__.py
django_covid19/admin.py
django_covid19/apps.py
django_covid19/filters.py
django_covid19/models.py
django_covid19/serializers.py
django_covid19/settings.py
django_covid19/signals.py
django_covid19/tests.py
django_covid19/urls.py
django_covid19/views.py
django_covid19/__pycache__/__init__.cpython-36.pyc
django_covid19/__pycache__/admin.cpython-36.pyc
django_covid19/__pycache__/apps.cpython-36.pyc
django_covid19/__pycache__/filters.cpython-36.pyc
django_covid19/__pycache__/models.cpython-36.pyc
django_covid19/__pycache__/serializers.cpython-36.pyc
django_covid19/__pycache__/settings.cpython-36.pyc
django_covid19/__pycache__/signals.cpython-36.pyc
django_covid19/__pycache__/test.cpython-36.pyc
django_covid19/__pycache__/tests.cpython-36.pyc
django_covid19/__pycache__/urls.cpython-36.pyc
django_covid19/__pycache__/views.cpython-36.pyc
django_covid19/fixtures/city.json
django_covid19/fixtures/country.json
django_covid19/fixtures/province.json
django_covid19/fixtures/statistics.json
django_covid19/locale/zh_Hans/LC_MESSAGES/django.mo
django_covid19/locale/zh_Hans/LC_MESSAGES/django.po
django_covid19/management/__init__.py
django_covid19-0.4rc1.dist-info/LICENSE
django_covid19-0.4rc1.dist-info/METADATA
django_covid19-0.4rc1.dist-info/WHEEL
django_covid19-0.4rc1.dist-info/top_level.txt
django_covid19-0.4rc1.dist-info/RECORD
