Metadata-Version: 2.1
Name: django-covid19
Version: 0.4rc1
Summary: A django app of covid-19 API in countries around the world, provinces and cities in China, and states in the USA.
Home-page: https://github.com/leafcoder/django-covid19
Author: leafcoder
Author-email: leafcoder@gmail.com
License: MIT
Keywords: python django covid19 2019-ncov app
Platform: UNKNOWN
Classifier: Development Status :: 5 - Production/Stable
Classifier: Environment :: Web Environment
Classifier: Framework :: Django
Classifier: Framework :: Django :: 2.0
Classifier: Framework :: Django :: 2.1
Classifier: Framework :: Django :: 2.2
Classifier: Intended Audience :: Developers
Classifier: License :: OSI Approved :: MIT License
Classifier: Natural Language :: Chinese (Simplified)
Classifier: Operating System :: OS Independent
Classifier: Programming Language :: Python
Classifier: Programming Language :: Python :: 3
Classifier: Programming Language :: Python :: 3 :: Only
Classifier: Programming Language :: Python :: 3.5
Classifier: Programming Language :: Python :: 3.6
Classifier: Programming Language :: Python :: 3.7
Classifier: Topic :: Internet :: WWW/HTTP
Classifier: Topic :: Internet :: WWW/HTTP :: Dynamic Content
Classifier: Topic :: Software Development :: Libraries
Classifier: Topic :: Software Development :: Libraries :: Python Modules
Requires-Dist: django-crontab (==0.7.1)
Requires-Dist: django-filter (==2.2.0)
Requires-Dist: djangorestframework (==3.11.0)
Requires-Dist: Scrapy (==2.0.1)
Requires-Dist: scrapy-djangoitem (==1.1.1)
Requires-Dist: django-mysql (==3.5.0)
